<?xml version="1.0" encoding="utf-8"?>
<Defs>
  <AlienRace.ThingDef_AlienRace ParentName="HumanRace">
    <defName>ReviaRaceAlien</defName>
    <label>Revia</label>
    <description>A bloodthirsty vulpine near-human.</description>
    <alienRace>
      <generalSettings>
        <maleGenderProbability>0.0000000000001</maleGenderProbability>
        <forcedRaceTraitEntries>
          <li>
            <defName>Bloodlust</defName>
          </li>
          <li>
            <defName>Beauty</defName>
            <degree>1</degree>
            <chance>40</chance>
          </li>
          <li>
            <defName>Beauty</defName>
            <degree>2</degree>
            <chance>30</chance>
          </li>
        </forcedRaceTraitEntries>
        <disallowedTraits>
          <li>
            <defName>Kind</defName>
          </li>
          <li>
            <defName>Wimp</defName>
          </li>
        </disallowedTraits>
        
        <allowHumanBios>false</allowHumanBios>
        <humanRecipeImport>true</humanRecipeImport>
        <alienPartGenerator>
          <colorChannels>
            <li>
              <name>skin</name>
              <first Class="ColorGenerator_Options">
                <options>
                  <li>
                    <weight>10</weight>
                    <min>RGBA(238,207,180,255)</min>
                    <max>RGBA(255,224,196,255)</max>
                  </li>
                  <li>
                    <weight>10</weight>
                    <only>RGBA(255,224,196,255)</only>
                  </li>
                  <li>
                    <weight>10</weight>
                    <only>RGBA(255,220,177,255)</only>
                  </li>
                  <li>
                    <weight>10</weight>
                    <only>RGBA(253,228,200,255)</only>
                  </li>
                  <li>
                    <weight>10</weight>
                    <only>RGBA(238,207,180,255)</only>
                  </li>
                </options>
              </first>
              <second Class="ColorGenerator_Options">
                <options>
                  <li>
                    <weight>10</weight>
                    <only>RGBA(255,224,196,255)</only>
                  </li>
                </options>
              </second>
            </li>
            <li>
              <name>hair</name>
              <first Class="ColorGenerator_Options">
                <options>
                  <!-- Blondes -->
                  <li>
                    <weight>15</weight>
                    <min>RGBA(161,121,48,255)</min>
                    <max>RGBA(180,130,65,255)</max>
                  </li>
                  <li>
                    <weight>10</weight>
                    <min>RGBA(180,170,65,255)</min>
                    <max>RGBA(225,200,90,255)</max>
                  </li>
                  <!-- Redheads -->
                  <li>
                    <weight>15</weight>
                    <min>RGBA(225,98,29,255)</min>
                    <max>RGBA(240,140,55,255)</max>
                  </li>
                  <!-- Brunettes -->
                  <li>
                    <weight>20</weight>
                    <min>RGBA(45,23,14,255)</min>
                    <max>RGBA(109,71,14,255)</max>
                  </li>
                  <!-- Ravens -->
                  <li>
                    <weight>20</weight>
                    <min>RGBA(2,2,2,255)</min>
                    <max>RGBA(33,33,2,255)</max>
                  </li>
                </options>
              </first>
              <second Class="ColorGenerator_Options">
                <options>
                  <li>
                    <weight>10</weight>
                    <only>RGBA(255,255,255,255)</only>
                  </li>
                </options>
              </second>
            </li>
          </colorChannels>
          <bodyTypes Inherit="false">
            <li>Thin</li>
            <li>Female</li>
            <li MayRequire="Ludeon.RimWorld.Biotech">Baby</li>
            <li MayRequire="Ludeon.RimWorld.Biotech">Child</li>
		  </bodyTypes>          
          <bodyAddons>
            <li>
              <scaleWithPawnDrawsize>true</scaleWithPawnDrawsize>
							<debug>false</debug>
              <path>Things/Tails/Tail1</path>
              <bodyPartLabel>tail</bodyPartLabel>
              <inFrontOfBody>false</inFrontOfBody>
              <drawnInBed>false</drawnInBed>
              <drawnDesiccated>false</drawnDesiccated>
              <colorChannel>hair</colorChannel>
              <shaderType>CutoutComplex</shaderType>
              <hediffGraphics>
                <ReviaRaceSoulreapTier1>Things/Tails/Tail1</ReviaRaceSoulreapTier1>
                <ReviaRaceSoulreapTier2>Things/Tails/Tail2</ReviaRaceSoulreapTier2>
                <ReviaRaceSoulreapTier3>Things/Tails/Tail3</ReviaRaceSoulreapTier3>
                <ReviaRaceSoulreapTier4>Things/Tails/Tail4</ReviaRaceSoulreapTier4>
                <ReviaRaceSoulreapTier5>Things/Tails/Tail5</ReviaRaceSoulreapTier5>
                <ReviaRaceSoulreapTier6>Things/Tails/Tail6</ReviaRaceSoulreapTier6>
                <ReviaRaceSoulreapTier7>Things/Tails/Tail7</ReviaRaceSoulreapTier7>
                <ReviaRaceSoulreapTier8>Things/Tails/Tail8</ReviaRaceSoulreapTier8>
                <ReviaRaceSoulreapTier9>Things/Tails/Tail9</ReviaRaceSoulreapTier9>
              </hediffGraphics>
              <offsets>
                <south>
                  <offset>(0.32, 0.0)</offset>
                  <bodyTypes>
                    <Female>(-0.38, 0.12)</Female>
                    <Thin>(-0.38, 0.12)</Thin>
                    <Baby MayRequire="ludeon.rimworld.biotech">(-0.35, 0.2)</Baby>
					<Child MayRequire="ludeon.rimworld.biotech">(-0.35, 0.3)</Child>                    
                  </bodyTypes>
                  <headTypes>
                    <Female_AverageNormal>(0, 0)</Female_AverageNormal>
                    <Female_AveragePointy>(0, 0)</Female_AveragePointy>
                    <Female_AverageWide>(0, 0)</Female_AverageWide>
                  </headTypes>
                </south>
                <north>
                  <offset>(-0.008, -0.44)</offset>
                  <bodyTypes>
                    <Female>(-0.07, 0.02)</Female>
                    <Thin>(-0.07, 0.02)</Thin>
                    <Baby MayRequire="ludeon.rimworld.biotech">(-0.015, 0.14)</Baby>
					<Child MayRequire="ludeon.rimworld.biotech">(-0.015, 0.14)</Child>
                  </bodyTypes>
                  <headTypes>
                    <Female_AverageNormal>(0, 0)</Female_AverageNormal>
                    <Female_AveragePointy>(0, 0)</Female_AveragePointy>
                    <Female_AverageWide>(0, 0)</Female_AverageWide>
                  </headTypes>
                </north>
                <east>
                  <offset>(0.44, -0.22)</offset>
                  <bodyTypes>
                    <Female>(-0.07, -0.17)</Female>
                    <Thin>(-0.14, -0.22)</Thin>
                    <Baby MayRequire="ludeon.rimworld.biotech">(-0.33, 0.08)</Baby>
					<Child MayRequire="ludeon.rimworld.biotech">(-0.235, 0.03)</Child>
                  </bodyTypes>
                  <headTypes>
                    <Female_AverageNormal>(0, 0)</Female_AverageNormal>
                    <Female_AveragePointy>(0, 0)</Female_AveragePointy>
                    <Female_AverageWide>(0, 0)</Female_AverageWide>
                  </headTypes>
                </east>
              </offsets>
            </li>
            <li>
              <scaleWithPawnDrawsize>true</scaleWithPawnDrawsize>
			  <debug>true</debug>
              <path>Things/Ears/EarLeft</path>
              <bodyPartLabel>left ear</bodyPartLabel>
              <inFrontOfBody>true</inFrontOfBody>
              <drawnInBed>true</drawnInBed>
              <drawnDesiccated>false</drawnDesiccated>
              <colorChannel>hair</colorChannel>
              <shaderType>CutoutComplex</shaderType>
              <offsets>
                <south>
                  <offset>(0.42, -0.26)</offset>
                  <bodyTypes>
                    <Female>(-0.475, 0.57)</Female>
                    <Thin>(-0.475, 0.57)</Thin>
                    <Baby MayRequire="ludeon.rimworld.biotech">(-0.40, 0.56)</Baby>
					<Child MayRequire="ludeon.rimworld.biotech">(-0.40, 0.56)</Child>                    
                  </bodyTypes>
                  <headTypes>
                    <Female_AverageNormal>(0, 0)</Female_AverageNormal>
                    <Female_AveragePointy>(0, 0)</Female_AveragePointy>
                    <Female_AverageWide>(0, 0)</Female_AverageWide>
                  </headTypes>
                </south>
                <north>
                  <offset>(-0.04, -0.52)</offset>
                  <bodyTypes>
                    <Female>(0.05, 0.9)</Female>
                    <Thin>(0.05, 0.9)</Thin>
                    <Baby MayRequire="ludeon.rimworld.biotech">(-0.007,0.83)</Baby>
					<Child MayRequire="ludeon.rimworld.biotech">(-0.007,0.83)</Child>
                  </bodyTypes>
                  <headTypes>
                    <Female_AverageNormal>(0, 0)</Female_AverageNormal>
                    <Female_AveragePointy>(0, 0)</Female_AveragePointy>
                    <Female_AverageWide>(0, 0)</Female_AverageWide>
                  </headTypes>
                </north>
                <east>
                  <offset>(0.42, -0.22)</offset>
                  <bodyTypes>
                    <Female>(-0.375, 0.57)</Female>
                    <Thin>(-0.375, 0.57)</Thin>
                    <Baby MayRequire="ludeon.rimworld.biotech">(-0.4,0.47)</Baby>
					<Child MayRequire="ludeon.rimworld.biotech">(-0.4,0.51)</Child>
                  </bodyTypes>
                  <headTypes>
                    <Female_AverageNormal>(0, 0)</Female_AverageNormal>
                    <Female_AveragePointy>(0, 0)</Female_AveragePointy>
                    <Female_AverageWide>(0, 0)</Female_AverageWide>
                  </headTypes>
                </east>
              </offsets>
            </li>
            <li>
              <scaleWithPawnDrawsize>true</scaleWithPawnDrawsize>
			  <debug>false</debug>
              <path>Things/Ears/EarRight</path>
              <bodyPartLabel>right ear</bodyPartLabel>
              <inFrontOfBody>true</inFrontOfBody>
              <drawnInBed>true</drawnInBed>
              <drawnDesiccated>false</drawnDesiccated>
              <colorChannel>hair</colorChannel>
              <shaderType>CutoutComplex</shaderType>
              <offsets>
                <south>
                  <offset>(0.42, -0.26)</offset>
                  <bodyTypes>
                    <Female>(-0.375, 0.57)</Female>
                    <Thin>(-0.375, 0.57)</Thin>
                    <Baby MayRequire="ludeon.rimworld.biotech">(-0.45, 0.56)</Baby>
					<Child MayRequire="ludeon.rimworld.biotech">(-0.45, 0.56)</Child>
                  </bodyTypes>
                  <headTypes>
                    <Female_AverageNormal>(0, 0)</Female_AverageNormal>
                    <Female_AveragePointy>(0, 0)</Female_AveragePointy>
                    <Female_AverageWide>(0, 0)</Female_AverageWide>
                  </headTypes>
                </south>
                <north>
                  <offset>(0.04, -0.52)</offset>
                  <bodyTypes>
                    <Female>(-0.05, 0.9)</Female>
                    <Thin>(-0.05, 0.9)</Thin>
                    <Baby MayRequire="ludeon.rimworld.biotech">(-0.01,0.83)</Baby>
					<Child MayRequire="ludeon.rimworld.biotech">(-0.01,0.83)</Child>
                  </bodyTypes>
                  <headTypes>
                    <Female_AverageNormal>(0, 0)</Female_AverageNormal>
                    <Female_AveragePointy>(0, 0)</Female_AveragePointy>
                    <Female_AverageWide>(0, 0)</Female_AverageWide>
                  </headTypes>
                </north>
                <east>
                  <layerOffset>-1</layerOffset>
                  <offset>(0.42, -0.22)</offset>
                  <bodyTypes>
                    <Female>(-0.375, 0.57)</Female>
                    <Thin>(-0.375, 0.57)</Thin>
                    <Baby MayRequire="ludeon.rimworld.biotech">(-0.46,0.46)</Baby>
					<Child MayRequire="ludeon.rimworld.biotech">(-0.46,0.46)</Child>
                  </bodyTypes>
                  <headTypes>
                    <Female_AverageNormal>(0, 0)</Female_AverageNormal>
                    <Female_AveragePointy>(0, 0)</Female_AveragePointy>
                    <Female_AverageWide>(0, 0)</Female_AverageWide>
                  </headTypes>
                </east>
              </offsets>
            </li>
          </bodyAddons>
        </alienPartGenerator>
      </generalSettings>
      <raceRestriction>
        <recipeList>
          <li>ReviaRaceBloodstoneToPalestone</li>
          <li>ReviaRaceCraftBloodRune</li>
          <li>ReviaRaceConsecrateBloodRune</li>
          <li>ReviaRaceSacrificeElephantTusk</li>
          <li>ReviaRaceConsecrateBloodRuneGreater</li>
          <li>ReviaRaceCraftGreaterBloodRune</li>
          <li>ReviaRaceSacrificeCorpse</li>
          <li>ReviaRaceConsecrateBloodRuneLesser</li>
          <li>ReviaRaceCraftLesserBloodRune</li>
          <li>ReviaRaceSacrificeRawMeat</li>
          <li>ReviaRaceSacrificeThrumboHorn</li>
        </recipeList>
        <researchList>
          <li>
            <projects>
              <li>ReviaRaceAdvancedEquipment</li>
              <li>ReviaRaceBloodBenediction</li>
              <li>ReviaRaceBasicEquipment</li>
              <li>ReviaRaceIntermediateEquipment</li>
              <li>ReviaRaceReligionBase</li>
              <li>ReviaRaceConsecratedWeaponry</li>
            </projects>
          </li>
        </researchList>
      </raceRestriction>
    </alienRace>
    <statBases>
      <MarketValue>3500</MarketValue>
      <MoveSpeed>5.25</MoveSpeed>
      <Flammability>1.0</Flammability>
      <ComfyTemperatureMin>0</ComfyTemperatureMin>
      <ComfyTemperatureMax>36</ComfyTemperatureMax>
      <LeatherAmount>45</LeatherAmount>
      <ResearchSpeed>0.90</ResearchSpeed>
      <MiningSpeed>1.25</MiningSpeed>
      <SocialImpact>0.95</SocialImpact>
      <MeleeDodgeChance>1.30</MeleeDodgeChance>
    </statBases>
    <tools Inherit="false">
      <li>
        <label>left fist</label>
        <capacities>
          <li>Blunt</li>
        </capacities>
        <power>7</power>
        <cooldownTime>1.2</cooldownTime>
        <linkedBodyPartsGroup>RightHand</linkedBodyPartsGroup>
        <surpriseAttack>
          <extraMeleeDamages>
            <li>
              <def>Stun</def>
              <amount>25</amount>
            </li>
          </extraMeleeDamages>
        </surpriseAttack>
      </li>
      <li>
        <label>right fist</label>
        <capacities>
          <li>Blunt</li>
        </capacities>
        <power>7</power>
        <cooldownTime>1.2</cooldownTime>
        <linkedBodyPartsGroup>LeftHand</linkedBodyPartsGroup>
        <surpriseAttack>
          <extraMeleeDamages>
            <li>
              <def>Stun</def>
              <amount>25</amount>
            </li>
          </extraMeleeDamages>
        </surpriseAttack>
      </li>
      <li>
        <label>teeth</label>
        <capacities>
          <li>Bite</li>
        </capacities>
        <power>14</power>
        
        <cooldownTime>1.8</cooldownTime>
        <linkedBodyPartsGroup>Teeth</linkedBodyPartsGroup>
        <chanceFactor>0.4</chanceFactor>
      </li>
    </tools>
    <race>
      <thinkTreeMain>Humanlike</thinkTreeMain>
      <thinkTreeConstant>HumanlikeConstant</thinkTreeConstant>
      <intelligence>Humanlike</intelligence>
      <makesFootprints>true</makesFootprints>
      <lifeExpectancy>110</lifeExpectancy>
      <nameCategory>HumanStandard</nameCategory>
      <body>ReviaRaceBody</body>
      <baseBodySize>0.95</baseBodySize>
      <baseHealthScale>1.15</baseHealthScale>
      <foodType>OmnivoreHuman</foodType>
      <gestationPeriodDays>18</gestationPeriodDays>
      <litterSizeCurve Inherit="false">
        <points>
          <li>(0.5, 0)</li>
          <li>(1, 1)</li>
          <li>(1.01, 0.02)</li>
          <li>(3.5, 0)</li>
        </points>
      </litterSizeCurve>
		<lifeStageAges>
			<li>
				<def>HumanlikeBaby</def>
				<minAge>0</minAge>
			</li>
			<li>
				<def>HumanlikeChild</def>
				<minAge>3</minAge>
			</li>
			<li MayRequire="Ludeon.RimWorld.Biotech">
				<def>HumanlikePreTeenager</def>
				<minAge>9</minAge>
			</li>
			<li>
				<def>HumanlikeTeenager</def>
				<minAge>13</minAge>
			</li>
			<li>
				<def>HumanlikeAdult</def>
				<minAge>18</minAge>
			</li>
		</lifeStageAges>
		<lifeStageWorkSettings MayRequire="Ludeon.RimWorld.Biotech">
			<Firefighter>7</Firefighter>
			<Patient>0</Patient>
			<Doctor>10</Doctor>
			<PatientBedRest>0</PatientBedRest>
			<Childcare MayRequire="Ludeon.RimWorld.Biotech">0</Childcare>
			<BasicWorker>7</BasicWorker>
			<Warden>10</Warden>
			<Handling>7</Handling>
			<Cooking>7</Cooking>
			<Hunting>7</Hunting>
			<Construction>10</Construction>
			<Growing>7</Growing>
			<Mining>7</Mining>
			<PlantCutting>7</PlantCutting>
			<Smithing>13</Smithing>
			<Tailoring>7</Tailoring>
			<Art>10</Art>
			<Crafting>7</Crafting>
			<Hauling>3</Hauling>
			<Cleaning>3</Cleaning>
			<Research>13</Research>
		</lifeStageWorkSettings>		
      <soundMeleeHitPawn>Pawn_Melee_Punch_HitPawn</soundMeleeHitPawn>
      <soundMeleeHitBuilding>Pawn_Melee_Punch_HitBuilding</soundMeleeHitBuilding>
      <soundMeleeMiss>Pawn_Melee_Punch_Miss</soundMeleeMiss>      
      <ageGenerationCurve Inherit="false">
        <points>
          <li MayRequire="Ludeon.RimWorld.Biotech">(0,0)</li>
          <li MayRequire="Ludeon.RimWorld.Biotech">(0.001,43)</li>
          <li MayRequire="Ludeon.RimWorld.Biotech">(8,86)</li>
          <li MayRequire="Ludeon.RimWorld.Biotech">(9.5,110)</li>  <!-- Exclude 9.5-10 years to avoid spawning pawns who are very close to becoming adults -->  
          <li MayRequire="Ludeon.RimWorld.Biotech">(9.51,0)</li>  
          <li MayRequire="Ludeon.RimWorld.Biotech">(10,0)</li>      
          <li MayRequire="Ludeon.RimWorld.Biotech">(10.001,110)</li><!-- End exclude -->
          <li MayRequire="Ludeon.RimWorld.Biotech">(13.999,110)</li>
          <li>(14,0)</li>
          <li MayRequire="Ludeon.RimWorld.Biotech">(14.001,110)</li>
          <li>(16,100)</li>
          <li>(20,100)</li>
          <li>(30,40)</li>
          <li>(35,30)</li>
          <li>(40,20)</li>
          <li>(50,10)</li>
          <li>(60,5)</li>
          <li>(70,5)</li>
          <li>(80,3)</li>
          <li>(90,2)</li>
          <li>(100,1)</li>
          <li>(110,0)</li>                 
        </points>
      </ageGenerationCurve>      
      <hediffGiverSets>
        <li>OrganicStandard</li>
      </hediffGiverSets>
    </race>
    <comps>
      <li>
        <compClass>ReviaRace.Comps.SoulReaper</compClass>
      </li>
      <li>
        <compClass>ReviaRace.Comps.ReviaRaceOnSpawn</compClass>
      </li>
    </comps>
  </AlienRace.ThingDef_AlienRace>
</Defs>